kaya_decomposition/__init__.py
kaya_decomposition/all_sectors.py
kaya_decomposition/factors.py
kaya_decomposition/lmdi.py
kaya_decomposition/lmdi_cumulative.py
kaya_decomposition/savings.py
kaya_decomposition/utils.py
kaya_decomposition/variables.py
kaya_decomposition/constants/__init__.py
kaya_decomposition/constants/input_variables.py
kaya_decomposition/constants/kaya_factors.py
kaya_decomposition/constants/kaya_variables.py
kaya_decomposition/constants/lmdi.py
kaya_decomposition/constants/lmdi_cumulative.py
kaya_decomposition/constants/savings.py
kaya_decomposition-0.4.0.dist-info/METADATA
kaya_decomposition-0.4.0.dist-info/WHEEL
kaya_decomposition-0.4.0.dist-info/licenses/LICENSE
kaya_decomposition-0.4.0.dist-info/RECORD
