Metadata-Version: 2.4
Name: kaya-decomposition
Version: 0.4.0
Summary: Kaya decomposition analysis for integrated-assessment scenario data
Project-URL: Homepage, https://github.com/zacharyschmidt/kaya-decomposition
Project-URL: Repository, https://github.com/zacharyschmidt/kaya-decomposition
Project-URL: Documentation, https://github.com/zacharyschmidt/kaya-decomposition#readme
Project-URL: Bug Tracker, https://github.com/zacharyschmidt/kaya-decomposition/issues
Author-email: Zachary Schmidt <zacharym.schmidt@gmail.com>
Maintainer-email: Zachary Schmidt <zacharym.schmidt@gmail.com>
License-Expression: Apache-2.0
License-File: LICENSE
Keywords: climate,decomposition,emissions,iam,iamc,kaya
Classifier: Development Status :: 4 - Beta
Classifier: Intended Audience :: Science/Research
Classifier: License :: OSI Approved :: Apache Software License
Classifier: Programming Language :: Python :: 3
Classifier: Programming Language :: Python :: 3.10
Classifier: Programming Language :: Python :: 3.11
Classifier: Programming Language :: Python :: 3.12
Classifier: Programming Language :: Python :: 3.13
Classifier: Topic :: Scientific/Engineering
Requires-Python: >=3.10
Requires-Dist: pyam-iamc>=2.0.0
Provides-Extra: dev
Requires-Dist: pytest-cov>=4.1.0; extra == 'dev'
Requires-Dist: pytest>=8.0.0; extra == 'dev'
